<?xml version="1.0" encoding="UTF-8"?>
<rootTag>
<Award>
<AwardTitle><![CDATA[CT-ISG:   Collaborative Research:  Incentives, Insurance and Audited Reputation:   An Economic Approach to Controlling Spam]]></AwardTitle>
<AGENCY>NSF</AGENCY>
<AwardEffectiveDate>01/01/2009</AwardEffectiveDate>
<AwardExpirationDate>06/30/2011</AwardExpirationDate>
<AwardTotalIntnAmount>351562.00</AwardTotalIntnAmount>
<AwardAmount>351562</AwardAmount>
<AwardInstrument>
<Value>Standard Grant</Value>
</AwardInstrument>
<Organization>
<Code>05050000</Code>
<Directorate>
<Abbreviation>CSE</Abbreviation>
<LongName>Direct For Computer &amp; Info Scie &amp; Enginr</LongName>
</Directorate>
<Division>
<Abbreviation>CNS</Abbreviation>
<LongName>Division Of Computer and Network Systems</LongName>
</Division>
</Organization>
<ProgramOfficer>
<SignBlockName>Samuel M. Weber</SignBlockName>
<PO_EMAI/>
<PO_PHON/>
</ProgramOfficer>
<AbstractNarration><![CDATA[ABSTRACT:&lt;br/&gt;&lt;br/&gt;The Internet is plagued by security problems including spam, threatening its legitimate role as the engine of growth in the new millennium. While technology makes admirable progress against cyber-security problems, the problem is not one of technology alone. Cyber security is part of a framework that encompasses technological, economic and social issues. The availability of technological solutions needs to be supplemented by service providers accepting responsibility for deploying technologies efficiently. Deployment of solutions and assignment of responsibility today tend to focus on a network provider's accountability to its own customers. In the decentralized Internet, allocation of accountability for potential impact on a remote network is important. This research seeks to direct investments to minimize impact on destination networks by efficient allocation of incentives. Security threats render the Internet a risky environment, and insurance mechanisms can seek to enhance productive and secure use of the Internet by risk management.  This project uses game theoretic models to study allocation of incentives among mail service providers to reduce global incidence of spam. This project will develop incentive and insurance mechanisms with the provision for certifying providers who voluntarily accept responsibility for damage to rest of the network, conduct empirical studies of the patterns of spam observed on Internet today for refining the analytical model, and experimentally test and validate the mechanisms and model. This research seeks to start an evolution of the Internet into an accountable and well-organized environment]]></AbstractNarration>
<MinAmdLetterDate>08/15/2008</MinAmdLetterDate>
<MaxAmdLetterDate>08/15/2008</MaxAmdLetterDate>
<ARRAAmount/>
<TRAN_TYPE>Grant</TRAN_TYPE>
<CFDA_NUM>47.070</CFDA_NUM>
<NSF_PAR_USE_FLAG>0</NSF_PAR_USE_FLAG>
<FUND_AGCY_CODE>4900</FUND_AGCY_CODE>
<AWDG_AGCY_CODE>4900</AWDG_AGCY_CODE>
<AwardID>0831338</AwardID>
<Investigator>
<FirstName>Andrew</FirstName>
<LastName>Whinston</LastName>
<PI_MID_INIT>B</PI_MID_INIT>
<PI_SUFX_NAME/>
<PI_FULL_NAME>Andrew B Whinston</PI_FULL_NAME>
<EmailAddress><![CDATA[abw@uts.cc.utexas.edu]]></EmailAddress>
<NSF_ID>000186235</NSF_ID>
<StartDate>08/15/2008</StartDate>
<EndDate/>
<RoleCode>Principal Investigator</RoleCode>
</Investigator>
<Institution>
<Name>University of Texas at Austin</Name>
<CityName>AUSTIN</CityName>
<ZipCode>787121139</ZipCode>
<PhoneNumber>5124716424</PhoneNumber>
<StreetAddress>110 INNER CAMPUS DR</StreetAddress>
<StreetAddress2/>
<CountryName>United States</CountryName>
<StateName>Texas</StateName>
<StateCode>TX</StateCode>
<CONGRESSDISTRICT>25</CONGRESSDISTRICT>
<CONGRESS_DISTRICT_ORG>TX25</CONGRESS_DISTRICT_ORG>
<ORG_UEI_NUM>V6AFQPN18437</ORG_UEI_NUM>
<ORG_LGL_BUS_NAME>UNIVERSITY OF TEXAS AT AUSTIN</ORG_LGL_BUS_NAME>
<ORG_PRNT_UEI_NUM>X5NKD2NFF2V3</ORG_PRNT_UEI_NUM>
</Institution>
<Performance_Institution>
<Name><![CDATA[University of Texas at Austin]]></Name>
<CityName>AUSTIN</CityName>
<StateCode>TX</StateCode>
<ZipCode>787121139</ZipCode>
<StreetAddress><![CDATA[110 INNER CAMPUS DR]]></StreetAddress>
<CountryCode>US</CountryCode>
<CountryName>United States</CountryName>
<StateName>Texas</StateName>
<CountryFlag>1</CountryFlag>
<CONGRESSDISTRICT>25</CONGRESSDISTRICT>
<CONGRESS_DISTRICT_PERF>TX25</CONGRESS_DISTRICT_PERF>
</Performance_Institution>
<ProgramElement>
<Code>7371</Code>
<Text>CYBER TRUST</Text>
</ProgramElement>
<ProgramReference>
<Code>9218</Code>
<Text>BASIC RESEARCH &amp; HUMAN RESORCS</Text>
</ProgramReference>
<ProgramReference>
<Code>HPCC</Code>
<Text>HIGH PERFORMANCE COMPUTING &amp; COMM</Text>
</ProgramReference>
<Appropriation>
<Code>0108</Code>
<Name>NSF RESEARCH &amp; RELATED ACTIVIT</Name>
<APP_SYMB_ID>040100</APP_SYMB_ID>
</Appropriation>
<Fund>
<Code>01000809DB</Code>
<Name><![CDATA[NSF RESEARCH & RELATED ACTIVIT]]></Name>
<FUND_SYMB_ID>040100</FUND_SYMB_ID>
</Fund>
<FUND_OBLG>2008~351562</FUND_OBLG>
</Award>
</rootTag>
