<?xml version="1.0" encoding="UTF-8"?>
<rootTag>
<Award>
<AwardTitle>SBIR Phase I:  A Miniaturized Sensor for Determining the Optical Properties of Aerosols</AwardTitle>
<AGENCY>NSF</AGENCY>
<AwardEffectiveDate>01/01/2009</AwardEffectiveDate>
<AwardExpirationDate>06/30/2009</AwardExpirationDate>
<AwardTotalIntnAmount>99998.00</AwardTotalIntnAmount>
<AwardAmount>99998</AwardAmount>
<AwardInstrument>
<Value>Standard Grant</Value>
</AwardInstrument>
<Organization>
<Code>15030000</Code>
<Directorate>
<Abbreviation>TIP</Abbreviation>
<LongName>Dir for Tech, Innovation, &amp; Partnerships</LongName>
</Directorate>
<Division>
<Abbreviation>TI</Abbreviation>
<LongName>Translational Impacts</LongName>
</Division>
</Organization>
<ProgramOfficer>
<SignBlockName>Juan E. Figueroa</SignBlockName>
<PO_EMAI/>
<PO_PHON/>
</ProgramOfficer>
<AbstractNarration>This Small Business Innovation Research (SBIR) Phase I project will develop a palm-sized and low-cost instrument for measuring the characteristics and distribution of airborne black carbon aerosol particles. Based on an existing analyzer, the optical property analyzer will use photoacoustic detection of aerosol light absorption in a miniature package. Current instruments are too large to be deployed easily in the upper atmosphere. The outcome of this proposed project is the development of a low cost but robust and accurate sensor that can be deployed on multiple platforms, manned and unmanned aircraft, balloons, ocean buoys, towers and in urban monitoring stations. &lt;br/&gt;&lt;br/&gt;If successful the broader impact of this activity will stem from rapid diffusion of knowledge that will occur once this new technology is made available to the international community. This new instrument circumvents the limitations of the technology that is currently being used in both research and monitoring applications. &lt;br/&gt;</AbstractNarration>
<MinAmdLetterDate>11/24/2008</MinAmdLetterDate>
<MaxAmdLetterDate>11/24/2008</MaxAmdLetterDate>
<ARRAAmount/>
<TRAN_TYPE>Grant</TRAN_TYPE>
<CFDA_NUM>47.084</CFDA_NUM>
<NSF_PAR_USE_FLAG>0</NSF_PAR_USE_FLAG>
<FUND_AGCY_CODE>4900</FUND_AGCY_CODE>
<AWDG_AGCY_CODE>4900</AWDG_AGCY_CODE>
<AwardID>0839402</AwardID>
<Investigator>
<FirstName>John</FirstName>
<LastName>Walker</LastName>
<PI_MID_INIT>W</PI_MID_INIT>
<PI_SUFX_NAME/>
<PI_FULL_NAME>John W Walker</PI_FULL_NAME>
<EmailAddress>jwalker@dropletmeasurement.com</EmailAddress>
<PI_PHON>3034405576</PI_PHON>
<NSF_ID>000506639</NSF_ID>
<StartDate>11/24/2008</StartDate>
<EndDate/>
<RoleCode>Principal Investigator</RoleCode>
</Investigator>
<Institution>
<Name>Droplet Measurement Technologies</Name>
<CityName>BOULDER</CityName>
<ZipCode>803015727</ZipCode>
<PhoneNumber>3034405576</PhoneNumber>
<StreetAddress>5710 FLATIRON PKWY</StreetAddress>
<StreetAddress2/>
<CountryName>United States</CountryName>
<StateName>Colorado</StateName>
<StateCode>CO</StateCode>
<CONGRESSDISTRICT>02</CONGRESSDISTRICT>
<CONGRESS_DISTRICT_ORG>CO02</CONGRESS_DISTRICT_ORG>
<ORG_UEI_NUM>ZZN7XB8KABJ4</ORG_UEI_NUM>
<ORG_LGL_BUS_NAME/>
<ORG_PRNT_UEI_NUM/>
</Institution>
<Performance_Institution>
<Name><![CDATA[Droplet Measurement Technologies]]></Name>
<CityName>BOULDER</CityName>
<StateCode>CO</StateCode>
<ZipCode>803015727</ZipCode>
<StreetAddress><![CDATA[5710 FLATIRON PKWY]]></StreetAddress>
<CountryCode>US</CountryCode>
<CountryName>United States</CountryName>
<StateName>Colorado</StateName>
<CountryFlag>1</CountryFlag>
<CONGRESSDISTRICT>02</CONGRESSDISTRICT>
<CONGRESS_DISTRICT_PERF>CO02</CONGRESS_DISTRICT_PERF>
</Performance_Institution>
<FoaInformation>
<Code>0308000</Code>
<Name>Industrial Technology</Name>
</FoaInformation>
<ProgramElement>
<Code>5371</Code>
<Text>SBIR Phase I</Text>
</ProgramElement>
<ProgramReference>
<Code>1517</Code>
<Text>ELECT, PHOTONICS, &amp; DEVICE TEC</Text>
</ProgramReference>
<ProgramReference>
<Code>1775</Code>
<Text>ELECTRONIC/PHOTONIC MATERIALS</Text>
</ProgramReference>
<ProgramReference>
<Code>7257</Code>
<Text>APPLICATS OF ADVANCED TECHNOLS</Text>
</ProgramReference>
<ProgramReference>
<Code>9139</Code>
<Text>INFORMATION INFRASTRUCTURE &amp; TECH APPL</Text>
</ProgramReference>
<ProgramReference>
<Code>HPCC</Code>
<Text>HIGH PERFORMANCE COMPUTING &amp; COMM</Text>
</ProgramReference>
<Appropriation>
<Code>0109</Code>
<Name>NSF RESEARCH &amp; RELATED ACTIVIT</Name>
<APP_SYMB_ID>040100</APP_SYMB_ID>
</Appropriation>
<Fund>
<Code>01000910DB</Code>
<Name><![CDATA[NSF RESEARCH & RELATED ACTIVIT]]></Name>
<FUND_SYMB_ID>040100</FUND_SYMB_ID>
</Fund>
<FUND_OBLG>2009~99998</FUND_OBLG>
</Award>
</rootTag>
