<?xml version="1.0" encoding="UTF-8"?>
<rootTag>
<Award>
<AwardTitle>MARGINS:  Collaborative Research:  Melting of Carbonate-bearing Sediments in Subduction Zones</AwardTitle>
<AGENCY>NSF</AGENCY>
<AwardEffectiveDate>07/01/2009</AwardEffectiveDate>
<AwardExpirationDate>06/30/2013</AwardExpirationDate>
<AwardTotalIntnAmount>54229.00</AwardTotalIntnAmount>
<AwardAmount>54229</AwardAmount>
<AwardInstrument>
<Value>Standard Grant</Value>
</AwardInstrument>
<Organization>
<Code>06040200</Code>
<Directorate>
<Abbreviation>GEO</Abbreviation>
<LongName>Directorate For Geosciences</LongName>
</Directorate>
<Division>
<Abbreviation>OCE</Abbreviation>
<LongName>Division Of Ocean Sciences</LongName>
</Division>
</Organization>
<ProgramOfficer>
<SignBlockName>Bilal U. Haq</SignBlockName>
<PO_EMAI/>
<PO_PHON/>
</ProgramOfficer>
<AbstractNarration>Dasgupta/Class&lt;br/&gt;&lt;br/&gt;This award is funded under the American Recovery and Reinvestment Act of 2009 (Public Law 111-2).&lt;br/&gt;&lt;br/&gt;Fund are provided for  conducting high-pressure experiments to investigate the fate of sediments as they are progressively subducted to greater depths.  In particular, two major questions are addressed that are relevant to the chief goals of the Subduction Factory initiative of MARGINS: (1) What is the effect of CO2 (in the form of carbonates) on the melting behavior of subducting sediments, and (2) What is the role of carbonated sediment melting on mass transfer and mass balance of major, trace, and volatile elements across the subduction factory?&lt;br/&gt;&lt;br/&gt;Broader impacts include support of a new young investigator and a female soft-money researcher (LDEO). It would also support a graduate student at Rice. And also involve undergraduate students in aspects of the research.&lt;br/&gt;</AbstractNarration>
<MinAmdLetterDate>06/29/2009</MinAmdLetterDate>
<MaxAmdLetterDate>06/29/2009</MaxAmdLetterDate>
<ARRAAmount>54229</ARRAAmount>
<TRAN_TYPE>Grant</TRAN_TYPE>
<CFDA_NUM>47.082</CFDA_NUM>
<NSF_PAR_USE_FLAG>0</NSF_PAR_USE_FLAG>
<FUND_AGCY_CODE>4900</FUND_AGCY_CODE>
<AWDG_AGCY_CODE>4900</AWDG_AGCY_CODE>
<AwardID>0841051</AwardID>
<Investigator>
<FirstName>Cornelia</FirstName>
<LastName>Class</LastName>
<PI_MID_INIT/>
<PI_SUFX_NAME/>
<PI_FULL_NAME>Cornelia Class</PI_FULL_NAME>
<EmailAddress>class@ldeo.columbia.edu</EmailAddress>
<NSF_ID>000125588</NSF_ID>
<StartDate>06/29/2009</StartDate>
<EndDate/>
<RoleCode>Principal Investigator</RoleCode>
</Investigator>
<Institution>
<Name>Columbia University</Name>
<CityName>NEW YORK</CityName>
<ZipCode>100276902</ZipCode>
<PhoneNumber>2128546851</PhoneNumber>
<StreetAddress>2960 Broadway</StreetAddress>
<StreetAddress2/>
<CountryName>United States</CountryName>
<StateName>New York</StateName>
<StateCode>NY</StateCode>
<CONGRESSDISTRICT>10</CONGRESSDISTRICT>
<CONGRESS_DISTRICT_ORG>NY10</CONGRESS_DISTRICT_ORG>
<ORG_DUNS_NUM>049179401</ORG_DUNS_NUM>
<ORG_LGL_BUS_NAME>TRUSTEES OF COLUMBIA UNIVERSITY IN THE CITY OF NEW YORK, THE</ORG_LGL_BUS_NAME>
<ORG_PRNT_DUNS_NUM>049179401</ORG_PRNT_DUNS_NUM>
</Institution>
<Performance_Institution>
<Name><![CDATA[Columbia University Lamont Doherty Earth Observatory]]></Name>
<CityName>Palisades</CityName>
<StateCode>NY</StateCode>
<ZipCode>10964</ZipCode>
<StreetAddress><![CDATA[Rt 9W]]></StreetAddress>
<CountryCode>US</CountryCode>
<CountryName>United States</CountryName>
<StateName>New York</StateName>
<CountryFlag>1</CountryFlag>
<CONGRESSDISTRICT>17</CONGRESSDISTRICT>
<CONGRESS_DISTRICT_PERF>NY17</CONGRESS_DISTRICT_PERF>
</Performance_Institution>
<FoaInformation>
<Code>0204000</Code>
<Name>Oceanography</Name>
</FoaInformation>
<ProgramElement>
<Code>1620</Code>
<Text>Marine Geology and Geophysics</Text>
</ProgramElement>
<ProgramReference>
<Code>0000</Code>
<Text>UNASSIGNED</Text>
</ProgramReference>
<ProgramReference>
<Code>1620</Code>
<Text>MARINE GEOLOGY AND GEOPHYSICS</Text>
</ProgramReference>
<ProgramReference>
<Code>6890</Code>
<Text>RECOVERY ACT ACTION</Text>
</ProgramReference>
<ProgramReference>
<Code>OTHR</Code>
<Text>OTHER RESEARCH OR EDUCATION</Text>
</ProgramReference>
<Appropriation>
<Code>01R9</Code>
<Name>RRA RECOVERY ACT</Name>
<APP_SYMB_ID>040101</APP_SYMB_ID>
</Appropriation>
<Fund>
<Code>01R00910DB</Code>
<Name><![CDATA[RRA RECOVERY ACT]]></Name>
<FUND_SYMB_ID>040101</FUND_SYMB_ID>
</Fund>
<FUND_OBLG>2009~54229</FUND_OBLG>
</Award>
</rootTag>
