<?xml version="1.0" encoding="UTF-8"?>
<rootTag>
<Award>
<AwardTitle><![CDATA[Collaborative Research: A 3D seismic investigation of the transition to seismogenic behavior along the southern Costa Rica subduction zone]]></AwardTitle>
<AGENCY>NSF</AGENCY>
<AwardEffectiveDate>08/15/2009</AwardEffectiveDate>
<AwardExpirationDate>09/30/2013</AwardExpirationDate>
<AwardTotalIntnAmount>988186.00</AwardTotalIntnAmount>
<AwardAmount>988186</AwardAmount>
<AwardInstrument>
<Value>Standard Grant</Value>
</AwardInstrument>
<Organization>
<Code>06040200</Code>
<Directorate>
<Abbreviation>GEO</Abbreviation>
<LongName>Directorate For Geosciences</LongName>
</Directorate>
<Division>
<Abbreviation>OCE</Abbreviation>
<LongName>Division Of Ocean Sciences</LongName>
</Division>
</Organization>
<ProgramOfficer>
<SignBlockName>Thomas Janecek</SignBlockName>
<PO_EMAI/>
<PO_PHON/>
</ProgramOfficer>
<AbstractNarration><![CDATA[This award is funded under the American Recovery and Reinvestment Act of 2009&lt;br/&gt;(Public Law 111-5). The proposed work is to examine changes in structural and physical properties along the southern Costa Rica subduction zone using 3D seismic imaging. At this location the plate boundary transitions from stable sliding to unstable sliding.  Understanding subduction zone processes is important for assessing geologic hazards such as earthquakes and tsunamis in these environments. In the proposed work,  seismically imaged structures will be used to address several fundamental problems such as 1) the structure and nature of large sediment lenses that are being subducted; b) the effects of existing seafloor topography on subduction processes; c) the changes in plate boundary fault geometry along the trench; and d) the variations in the structure of the upper plate along the subduction zone. This work will support the education and training of graduate students.  There is international collaboration with scientists from Spain, Germany and Costa Rica.  There is also a component of industry support.]]></AbstractNarration>
<MinAmdLetterDate>08/10/2009</MinAmdLetterDate>
<MaxAmdLetterDate>02/19/2013</MaxAmdLetterDate>
<ARRAAmount>988186</ARRAAmount>
<TRAN_TYPE>Grant</TRAN_TYPE>
<CFDA_NUM>47.082</CFDA_NUM>
<NSF_PAR_USE_FLAG>0</NSF_PAR_USE_FLAG>
<FUND_AGCY_CODE>4900</FUND_AGCY_CODE>
<AWDG_AGCY_CODE>4900</AWDG_AGCY_CODE>
<AwardID>0851380</AwardID>
<Investigator>
<FirstName>Kirk</FirstName>
<LastName>McIntosh</LastName>
<PI_MID_INIT>D</PI_MID_INIT>
<PI_SUFX_NAME/>
<PI_FULL_NAME>Kirk D McIntosh</PI_FULL_NAME>
<EmailAddress><![CDATA[kirk@ig.utexas.edu]]></EmailAddress>
<NSF_ID>000419979</NSF_ID>
<StartDate>08/10/2009</StartDate>
<EndDate/>
<RoleCode>Co-Principal Investigator</RoleCode>
</Investigator>
<Investigator>
<FirstName>Nathan</FirstName>
<LastName>Bangs</LastName>
<PI_MID_INIT>L</PI_MID_INIT>
<PI_SUFX_NAME/>
<PI_FULL_NAME>Nathan L Bangs</PI_FULL_NAME>
<EmailAddress><![CDATA[nathan@ig.utexas.edu]]></EmailAddress>
<NSF_ID>000088836</NSF_ID>
<StartDate>08/10/2009</StartDate>
<EndDate/>
<RoleCode>Principal Investigator</RoleCode>
</Investigator>
<Institution>
<Name>University of Texas at Austin</Name>
<CityName>AUSTIN</CityName>
<ZipCode>787121139</ZipCode>
<PhoneNumber>5124716424</PhoneNumber>
<StreetAddress>110 INNER CAMPUS DR</StreetAddress>
<StreetAddress2/>
<CountryName>United States</CountryName>
<StateName>Texas</StateName>
<StateCode>TX</StateCode>
<CONGRESSDISTRICT>25</CONGRESSDISTRICT>
<CONGRESS_DISTRICT_ORG>TX25</CONGRESS_DISTRICT_ORG>
<ORG_UEI_NUM>V6AFQPN18437</ORG_UEI_NUM>
<ORG_LGL_BUS_NAME>UNIVERSITY OF TEXAS AT AUSTIN</ORG_LGL_BUS_NAME>
<ORG_PRNT_UEI_NUM>X5NKD2NFF2V3</ORG_PRNT_UEI_NUM>
</Institution>
<Performance_Institution>
<Name><![CDATA[University of Texas at Austin]]></Name>
<CityName>AUSTIN</CityName>
<StateCode>TX</StateCode>
<ZipCode>787121139</ZipCode>
<StreetAddress><![CDATA[110 INNER CAMPUS DR]]></StreetAddress>
<CountryCode>US</CountryCode>
<CountryName>United States</CountryName>
<StateName>Texas</StateName>
<CountryFlag>1</CountryFlag>
<CONGRESSDISTRICT>25</CONGRESSDISTRICT>
<CONGRESS_DISTRICT_PERF>TX25</CONGRESS_DISTRICT_PERF>
</Performance_Institution>
<FoaInformation>
<Code>0204000</Code>
<Name>Oceanography</Name>
</FoaInformation>
<ProgramElement>
<Code>5720</Code>
<Text>OCEAN DRILLING PROGRAM</Text>
</ProgramElement>
<ProgramReference>
<Code>0000</Code>
<Text>UNASSIGNED</Text>
</ProgramReference>
<ProgramReference>
<Code>5720</Code>
<Text>OCEAN DRILLING PROGRAM</Text>
</ProgramReference>
<ProgramReference>
<Code>6890</Code>
<Text>RECOVERY ACT ACTION</Text>
</ProgramReference>
<ProgramReference>
<Code>OTHR</Code>
<Text>OTHER RESEARCH OR EDUCATION</Text>
</ProgramReference>
<Appropriation>
<Code>01R9</Code>
<Name>RRA RECOVERY ACT</Name>
<APP_SYMB_ID>040101</APP_SYMB_ID>
</Appropriation>
<Fund>
<Code>01R00910DB</Code>
<Name><![CDATA[RRA RECOVERY ACT]]></Name>
<FUND_SYMB_ID>040101</FUND_SYMB_ID>
</Fund>
<FUND_OBLG>2009~988186</FUND_OBLG>
</Award>
</rootTag>
